tracetree/__init__.py
tracetree/__main__.py
tracetree/cli.py
tracetree/core.py
tracetree-0.1.7.dist-info/licenses/LICENSE
tracetree-0.1.7.dist-info/METADATA
tracetree-0.1.7.dist-info/WHEEL
tracetree-0.1.7.dist-info/entry_points.txt
tracetree-0.1.7.dist-info/top_level.txt
tracetree-0.1.7.dist-info/RECORD
