Metadata-Version: 2.4
Name: tracetree
Version: 0.1.7
Summary: Universal traceability validation and rollup for requirements-to-tests mapping.
Author: Technoculture
License: MIT
Keywords: traceability,requirements,quality,verification,compliance
Classifier: Development Status :: 3 - Alpha
Classifier: Intended Audience :: Developers
Classifier: License :: OSI Approved :: MIT License
Classifier: Programming Language :: Python :: 3
Classifier: Programming Language :: Python :: 3.9
Classifier: Programming Language :: Python :: 3.10
Classifier: Programming Language :: Python :: 3.11
Classifier: Programming Language :: Python :: 3.12
Classifier: Topic :: Software Development :: Testing
Classifier: Topic :: Software Development :: Quality Assurance
Requires-Python: >=3.9
License-File: LICENSE
Requires-Dist: typer>=0.12.0
Dynamic: license-file
